mcp_server_again/__init__.py
mcp_server_again/__main__.py
mcp_server_again/mcp_server_again.py
mcp_server_again-0.1.0.dist-info/METADATA
mcp_server_again-0.1.0.dist-info/WHEEL
mcp_server_again-0.1.0.dist-info/entry_points.txt
mcp_server_again-0.1.0.dist-info/RECORD
